hashpipe/__init__.py
hashpipe/__main__.py
hashpipe/py.typed
hashpipe-0.9.2.data/scripts/hashpipe
hashpipe-0.9.2.dist-info/LICENSE
hashpipe-0.9.2.dist-info/METADATA
hashpipe-0.9.2.dist-info/WHEEL
hashpipe-0.9.2.dist-info/top_level.txt
hashpipe-0.9.2.dist-info/RECORD
