Metadata-Version: 2.1
Name: hashpipe
Version: 0.9.2
Summary: Regular expression match hasher
Home-page: https://github.com/scop/hashpipe
Author: Ville Skyttä
Author-email: ville.skytta@iki.fi
License: Apache License 2.0
Platform: UNKNOWN
Classifier: Development Status :: 4 - Beta
Classifier: Intended Audience :: Developers
Classifier: Intended Audience :: System Administrators
Classifier: License :: OSI Approved :: Apache Software License
Classifier: Programming Language :: Python :: 3 :: Only
Requires-Python: >=3.3
Requires-Dist: typing ; python_version < "3.5"
Provides-Extra: completion
Requires-Dist: argcomplete ; extra == 'completion'
